HISTORY.rst
MANIFEST.in
README.md
setup.py
django_usernameless.egg-info/PKG-INFO
django_usernameless.egg-info/SOURCES.txt
django_usernameless.egg-info/dependency_links.txt
django_usernameless.egg-info/not-zip-safe
django_usernameless.egg-info/requires.txt
django_usernameless.egg-info/top_level.txt
usernameless/__init__.py
usernameless/admin.py
usernameless/forms.py
usernameless/models.py
usernameless/receivers.py
usernameless/urls.py
usernameless/views.py