Metadata-Version: 1.0
Name: django-usernameless
Version: 0.1.0
Summary: Custom user without username for Django-1.5
Home-page: https://github.com/marconi/django-usernameless
Author: Marconi Moreto
Author-email: caketoad@gmail.com
License: UNKNOWN
Platform: UNKNOWN
